actbench/__init__.py
actbench/cli.py
actbench/py.typed
actbench/browser/__init__.py
actbench/browser/base.py
actbench/browser/fleet.py
actbench/clients/__init__.py
actbench/clients/base.py
actbench/clients/browseruse.py
actbench/clients/raccoonai.py
actbench/datasets/__init__.py
actbench/datasets/base.py
actbench/datasets/json.py
actbench/executor/__init__.py
actbench/executor/evaluator.py
actbench/executor/task_executor.py
actbench/storage/__init__.py
actbench-0.0.1a5.dist-info/METADATA
actbench-0.0.1a5.dist-info/WHEEL
actbench-0.0.1a5.dist-info/entry_points.txt
actbench-0.0.1a5.dist-info/licenses/LICENSE
actbench-0.0.1a5.dist-info/RECORD
