Metadata-Version: 2.4
Name: actbench
Version: 0.0.1a5
Summary: A framework for evaluating web automation agents and LAM systems.
Project-URL: Homepage, https://github.com/raccoonaihq/actbench
Project-URL: Repository, https://github.com/raccoonaihq/actbench
Author-email: Raccoon AI <team@flyingraccoon.tech>
License-Expression: MIT
License-File: LICENSE
Keywords: AI,LAM systems,agent evaluation,benchmarking,web automation
Classifier: Intended Audience :: Developers
Classifier: License :: OSI Approved :: MIT License
Classifier: Operating System :: MacOS
Classifier: Operating System :: Microsoft :: Windows
Classifier: Operating System :: OS Independent
Classifier: Operating System :: POSIX
Classifier: Operating System :: POSIX :: Linux
Classifier: Programming Language :: Python :: 3.12
Classifier: Topic :: Software Development :: Libraries :: Python Modules
Classifier: Typing :: Typed
Requires-Python: >=3.12
Requires-Dist: browser-use~=0.1.24
Requires-Dist: click~=8.1.8
Requires-Dist: langchain-openai~=0.3.7
Requires-Dist: langchain~=0.3.19
Requires-Dist: pydantic~=2.10.6
Requires-Dist: pyfiglet~=1.0.2
Requires-Dist: raccoonai~=0.1.0a6
Requires-Dist: rich~=13.9.4
